{"date": "2026-07-21", "updated": "12:45 PM", "generatedMs": 1784663113881, "today": {"calls": 9, "tgls": 4, "rate": 44.4, "rev": 0, "techs": [{"name": "Benjamin Wyllie", "calls": 1, "tgls": 1, "rate": 100.0, "rev": 0}, {"name": "Juan Tlatenchi", "calls": 1, "tgls": 1, "rate": 100.0, "rev": 0}, {"name": "Noah Weng", "calls": 1, "tgls": 1, "rate": 100.0, "rev": 0}, {"name": "Cole Pantol", "calls": 0, "tgls": 1, "rate": 0.0, "rev": 0}, {"name": "Nikko April", "calls": 2, "tgls": 0, "rate": 0.0, "rev": 0}, {"name": "Brandon Moreno", "calls": 1, "tgls": 0, "rate": 0.0, "rev": 0}, {"name": "Francisco Valencia", "calls": 1, "tgls": 0, "rate": 0.0, "rev": 0}, {"name": "Joe Mendoza", "calls": 1, "tgls": 0, "rate": 0.0, "rev": 0}, {"name": "Robert Silinzy", "calls": 1, "tgls": 0, "rate": 0.0, "rev": 0}], "sched": {"ran": 6, "same": 1, "samePct": 16.7, "sold": 1, "soldrev": 22313, "closeRate": 16.7, "techs": [{"name": "Noah Weng", "ran": 3, "same": 1, "sold": 0, "soldrev": 0, "samePct": 33.3}, {"name": "Andrew Trujillo", "ran": 1, "same": 0, "sold": 0, "soldrev": 0, "samePct": 0.0}, {"name": "Brandon Moreno", "ran": 1, "same": 0, "sold": 1, "soldrev": 22313, "samePct": 0.0}, {"name": "Juan Tlatenchi", "ran": 1, "same": 0, "sold": 0, "soldrev": 0, "samePct": 0.0}]}}, "hours": [{"hour": "00", "calls": 0, "tgls": 0, "rate": 0.0, "dcalls": 0, "dtgls": 0, "drate": 0.0}, {"hour": "01", "calls": 0, "tgls": 0, "rate": 0.0, "dcalls": 0, "dtgls": 0, "drate": 0.0}, {"hour": "02", "calls": 0, "tgls": 0, "rate": 0.0, "dcalls": 0, "dtgls": 0, "drate": 0.0}, {"hour": "03", "calls": 0, "tgls": 0, "rate": 0.0, "dcalls": 0, "dtgls": 0, "drate": 0.0}, {"hour": "04", "calls": 0, "tgls": 0, "rate": 0.0, "dcalls": 0, "dtgls": 0, "drate": 0.0}, {"hour": "05", "calls": 0, "tgls": 0, "rate": 0.0, "dcalls": 0, "dtgls": 0, "drate": 0.0}, {"hour": "06", "calls": 0, "tgls": 0, "rate": 0.0, "dcalls": 0, "dtgls": 0, "drate": 0.0}, {"hour": "07", "calls": 0, "tgls": 0, "rate": 0.0, "dcalls": 0, "dtgls": 0, "drate": 0.0}, {"hour": "08", "calls": 0, "tgls": 0, "rate": 0.0, "dcalls": 0, "dtgls": 0, "drate": 0.0}, {"hour": "09", "calls": 2, "tgls": 0, "rate": 0.0, "dcalls": 2, "dtgls": 0, "drate": 0.0}, {"hour": "10", "calls": 3, "tgls": 1, "rate": 33.3, "dcalls": 1, "dtgls": 1, "drate": 100.0}, {"hour": "11", "calls": 6, "tgls": 4, "rate": 66.7, "dcalls": 3, "dtgls": 3, "drate": 100.0}, {"hour": "12", "calls": 9, "tgls": 4, "rate": 44.4, "dcalls": 3, "dtgls": 0, "drate": 0.0}]}